Workbook

Sheet Resumo
A1: Estoque Vivo — posição de 25/09/2026
A2: Gerado a partir do app de controle de estoque. Os números vêm da aba Estoque.
A4: Itens cadastrados | B4: =COUNTA(Estoque!A2:A38) -> 37 | C4: Todos os SKUs da contagem do galpão.
A5: Unidades em estoque | B5: =SUM(Estoque!E2:E38) -> 6474 | C5: Soma de todas as peças.
A6: Valor em custo | B6: =SUM(Estoque!I2:I38) -> 120348.5 | C6: Valor total do estoque, a preço de custo.
A7: Itens sem estoque | B7: =COUNTIF(Estoque!J2:J38,"Sem estoque") -> 0 | C7: Saldo zero.
A8: Itens abaixo do mínimo | B8: =COUNTIF(Estoque!J2:J38,"Abaixo do mínimo") -> 0 | C8: Só acende depois que você preencher o estoque mínimo.
A9: Itens com saldo negativo | B9: =COUNTIF(Estoque!J2:J38,"Negativo") -> 0 | C9: Indica erro de lançamento — conferir na prateleira.
A11: Entradas no histórico | B11: =SUMIFS(Movimentos!$F$2:$F$300,Movimentos!$E$2:$E$300,"Entrada") -> 1441 | C11: Mercadoria recebida.
A12: Vendas no histórico | B12: =-SUMIFS(Movimentos!$F$2:$F$300,Movimentos!$E$2:$E$300,"Venda") -> 421 | C12: Peças baixadas por venda.
A13: Transferido ao ML Full | B13: =-SUMIFS(Movimentos!$F$2:$F$300,Movimentos!$E$2:$E$300,"Transferência") -> 765 | C13: Saiu do galpão, mas não foi venda.
A15: Como usar
A16: • As células amarelas da aba Estoque (mínimo, custo e preço de venda) já vêm preenchidas — edite direto ali se algum valor mudar.
A17: • Formato dessas colunas: número puro, sem R$ e sem ponto de milhar. Ex.: mínimo 50 · custo 12,90 · preço 27,50.
A18: • 9403 STD, 2900 e 8566 STD ainda estão sem preço de venda informado — só o custo.
A19: • As colunas Valor em custo, Situação e Vendido (histórico) são fórmulas — não digite nada nelas.
A20: • Esta planilha é uma foto do dia 25/09. O saldo que vale é o do app, que atualiza na hora.
A22: App do estoque: https://claude.ai/artifact/JiMT1jfH7Vc3MUYtYcDNG7

Sheet Estoque
A1: Item | B1: Código | C1: Categoria | D1: Unid. | E1: Quantidade | F1: Estoque mínimo | G1: Custo unit. (R$) | H1: Preço venda (R$) | I1: Valor em custo (R$) | J1: Situação | K1: Vendido (histórico)
A2: Anel 8126 STD | B2: 8126 STD | C2: Anéis | D2: un | E2: 289 | G2: 75 | H2: 142.25 | I2: =E2*G2 -> 21675 | J2: =IF(E2<0,"Negativo",IF(E2=0,"Sem estoque",IF(AND(F2>0,E2<=F2),"Abaixo do mínimo","OK"))) -> OK | K2: =-SUMIFS(Movimentos!$F$2:$F$300,Movimentos!$D$2:$D$300,$B2,Movimentos!$E$2:$E$300,"Venda") -> 2
A3: Anel SDA 6631 0,50 | B3: 6631 0,50 | C3: Anéis | D3: un | E3: 99 | G3: 75 | H3: 148.56 | I3: =E3*G3 -> 7425 | J3: =IF(E3<0,"Negativo",IF(E3=0,"Sem estoque",IF(AND(F3>0,E3<=F3),"Abaixo do mínimo","OK"))) -> OK | K3: =-SUMIFS(Movimentos!$F$2:$F$300,Movimentos!$D$2:$D$300,$B3,Movimentos!$E$2:$E$300,"Venda") -> 1
A4: Anel SDA 7092 | B4: 7092 | C4: Anéis | D4: un | E4: 22 | G4: 75 | H4: 127.94 | I4: =E4*G4 -> 1650 | J4: =IF(E4<0,"Negativo",IF(E4=0,"Sem estoque",IF(AND(F4>0,E4<=F4),"Abaixo do mínimo","OK"))) -> OK | K4: =-SUMIFS(Movimentos!$F$2:$F$300,Movimentos!$D$2:$D$300,$B4,Movimentos!$E$2:$E$300,"Venda") -> 3
A5: Anéis 8126 0,50 | B5: 8126 0,50 | C5: Anéis | D5: un | E5: 1 | G5: 75 | H5: 144.9 | I5: =E5*G5 -> 75 | J5: =IF(E5<0,"Negativo",IF(E5=0,"Sem estoque",IF(AND(F5>0,E5<=F5),"Abaixo do mínimo","OK"))) -> OK | K5: =-SUMIFS(Movimentos!$F$2:$F$300,Movimentos!$D$2:$D$300,$B5,Movimentos!$E$2:$E$300,"Venda") -> 3
A6: Anéis 9200 STD | B6: 9200 STD | C6: Anéis | D6: un | E6: 7 | G6: 75 | H6: 156.03 | I6: =E6*G6 -> 525 | J6: =IF(E6<0,"Negativo",IF(E6=0,"Sem estoque",IF(AND(F6>0,E6<=F6),"Abaixo do mínimo","OK"))) -> OK | K6: =-SUMIFS(Movimentos!$F$2:$F$300,Movimentos!$D$2:$D$300,$B6,Movimentos!$E$2:$E$300,"Venda") -> 11
A7: Anéis 9403 STD | B7: 9403 STD | C7: Anéis | D7: un | E7: 20 | G7: 75 | I7: =E7*G7 -> 1500 | J7: =IF(E7<0,"Negativo",IF(E7=0,"Sem estoque",IF(AND(F7>0,E7<=F7),"Abaixo do mínimo","OK"))) -> OK | K7: =-SUMIFS(Movimentos!$F$2:$F$300,Movimentos!$D$2:$D$300,$B7,Movimentos!$E$2:$E$300,"Venda") -> 0
A8: Bronzina de Biela SBB 1035-J 0,25 | B8: 1035-J | C8: Bronzina | D8: un | E8: 22 | G8: 32 | H8: 69.25 | I8: =E8*G8 -> 704 | J8: =IF(E8<0,"Negativo",IF(E8=0,"Sem estoque",IF(AND(F8>0,E8<=F8),"Abaixo do mínimo","OK"))) -> OK | K8: =-SUMIFS(Movimentos!$F$2:$F$300,Movimentos!$D$2:$D$300,$B8,Movimentos!$E$2:$E$300,"Venda") -> 2
A9: Jogo de Anel 7224 0,50 | B9: 7224 0,50 | C9: Jogo de Anel | D9: un | E9: 51 | G9: 75 | H9: 172.55 | I9: =E9*G9 -> 3825 | J9: =IF(E9<0,"Negativo",IF(E9=0,"Sem estoque",IF(AND(F9>0,E9<=F9),"Abaixo do mínimo","OK"))) -> OK | K9: =-SUMIFS(Movimentos!$F$2:$F$300,Movimentos!$D$2:$D$300,$B9,Movimentos!$E$2:$E$300,"Venda") -> 3
A10: Jogo de Anel 7224 STD | B10: 7224 STD | C10: Jogo de Anel | D10: un | E10: 35 | G10: 75 | H10: 126.81 | I10: =E10*G10 -> 2625 | J10: =IF(E10<0,"Negativo",IF(E10=0,"Sem estoque",IF(AND(F10>0,E10<=F10),"Abaixo do mínimo","OK"))) -> OK | K10: =-SUMIFS(Movimentos!$F$2:$F$300,Movimentos!$D$2:$D$300,$B10,Movimentos!$E$2:$E$300,"Venda") -> 8
A11: Retentor 1135 | B11: 1135 | C11: Retentor | D11: un | E11: 116 | G11: 12 | H11: 31.13 | I11: =E11*G11 -> 1392 | J11: =IF(E11<0,"Negativo",IF(E11=0,"Sem estoque",IF(AND(F11>0,E11<=F11),"Abaixo do mínimo","OK"))) -> OK | K11: =-SUMIFS(Movimentos!$F$2:$F$300,Movimentos!$D$2:$D$300,$B11,Movimentos!$E$2:$E$300,"Venda") -> 2
A12: Retentor 1942 | B12: 1942 | C12: Retentor | D12: un | E12: 558 | G12: 8 | H12: 12.32 | I12: =E12*G12 -> 4464 | J12: =IF(E12<0,"Negativo",IF(E12=0,"Sem estoque",IF(AND(F12>0,E12<=F12),"Abaixo do mínimo","OK"))) -> OK | K12: =-SUMIFS(Movimentos!$F$2:$F$300,Movimentos!$D$2:$D$300,$B12,Movimentos!$E$2:$E$300,"Venda") -> 117
A13: Retentor 2075 | B13: 2075 | C13: Retentor | D13: un | E13: 124 | G13: 8 | H13: 13.42 | I13: =E13*G13 -> 992 | J13: =IF(E13<0,"Negativo",IF(E13=0,"Sem estoque",IF(AND(F13>0,E13<=F13),"Abaixo do mínimo","OK"))) -> OK | K13: =-SUMIFS(Movimentos!$F$2:$F$300,Movimentos!$D$2:$D$300,$B13,Movimentos!$E$2:$E$300,"Venda") -> 0
A14: Retentor 2178 | B14: 2178 | C14: Retentor | D14: un | E14: 311 | G14: 8 | H14: 11.18 | I14: =E14*G14 -> 2488 | J14: =IF(E14<0,"Negativo",IF(E14=0,"Sem estoque",IF(AND(F14>0,E14<=F14),"Abaixo do mínimo","OK"))) -> OK | K14: =-SUMIFS(Movimentos!$F$2:$F$300,Movimentos!$D$2:$D$300,$B14,Movimentos!$E$2:$E$300,"Venda") -> 41
A15: Retentor 2283 | B15: 2283 | C15: Retentor | D15: un | E15: 268 | G15: 15 | H15: 28.18 | I15: =E15*G15 -> 4020 | J15: =IF(E15<0,"Negativo",IF(E15=0,"Sem estoque",IF(AND(F15>0,E15<=F15),"Abaixo do mínimo","OK"))) -> OK | K15: =-SUMIFS(Movimentos!$F$2:$F$300,Movimentos!$D$2:$D$300,$B15,Movimentos!$E$2:$E$300,"Venda") -> 6
A16: Retentor 2317 | B16: 2317 | C16: Retentor | D16: un | E16: 72 | G16: 8 | H16: 25.62 | I16: =E16*G16 -> 576 | J16: =IF(E16<0,"Negativo",IF(E16=0,"Sem estoque",IF(AND(F16>0,E16<=F16),"Abaixo do mínimo","OK"))) -> OK | K16: =-SUMIFS(Movimentos!$F$2:$F$300,Movimentos!$D$2:$D$300,$B16,Movimentos!$E$2:$E$300,"Venda") -> 0
A17: Retentor 2370 | B17: 2370 | C17: Retentor | D17: un | E17: 434 | G17: 7 | H17: 10.3 | I17: =E17*G17 -> 3038 | J17: =IF(E17<0,"Negativo",IF(E17=0,"Sem estoque",IF(AND(F17>0,E17<=F17),"Abaixo do mínimo","OK"))) -> OK | K17: =-SUMIFS(Movimentos!$F$2:$F$300,Movimentos!$D$2:$D$300,$B17,Movimentos!$E$2:$E$300,"Venda") -> 24
A18: Retentor 2371 (Shopee) | B18: 2371 | C18: Retentor | D18: un | E18: 359 | G18: 7 | H18: 20 | I18: =E18*G18 -> 2513 | J18: =IF(E18<0,"Negativo",IF(E18=0,"Sem estoque",IF(AND(F18>0,E18<=F18),"Abaixo do mínimo","OK"))) -> OK | K18: =-SUMIFS(Movimentos!$F$2:$F$300,Movimentos!$D$2:$D$300,$B18,Movimentos!$E$2:$E$300,"Venda") -> 0
A19: Retentor 2373 | B19: 2373 | C19: Retentor | D19: un | E19: 94 | G19: 6 | H19: 22.16 | I19: =E19*G19 -> 564 | J19: =IF(E19<0,"Negativo",IF(E19=0,"Sem estoque",IF(AND(F19>0,E19<=F19),"Abaixo do mínimo","OK"))) -> OK | K19: =-SUMIFS(Movimentos!$F$2:$F$300,Movimentos!$D$2:$D$300,$B19,Movimentos!$E$2:$E$300,"Venda") -> 7
... A36: Vedadores 9203 | B36: 9203 | C36: Vedador | D36: un | E36: 318 | G36: 9 | H36: 13.36 | I36: =E36*G36 -> 2862 | J36: =IF(E36<0,"Negativo",IF(E36=0,"Sem estoque",IF(AND(F36>0,E36<=F36),"Abaixo do mínimo","OK"))) -> OK | K36: =-SUMIFS(Movimentos!$F$2:$F$300,Movimentos!$D$2:$D$300,$B36,Movimentos!$E$2:$E$300,"Venda") -> 57
A37: 2900 | B37: 2900 | D37: un | E37: 50 | G37: 75 | I37: =E37*G37 -> 3750 | J37: =IF(E37<0,"Negativo",IF(E37=0,"Sem estoque",IF(AND(F37>0,E37<=F37),"Abaixo do mínimo","OK"))) -> OK | K37: =-SUMIFS(Movimentos!$F$2:$F$300,Movimentos!$D$2:$D$300,$B37,Movimentos!$E$2:$E$300,"Venda") -> 0
A38: 8566 STD | B38: 8566 STD | D38: un | E38: 20 | G38: 75 | I38: =E38*G38 -> 1500 | J38: =IF(E38<0,"Negativo",IF(E38=0,"Sem estoque",IF(AND(F38>0,E38<=F38),"Abaixo do mínimo","OK"))) -> OK | K38: =-SUMIFS(Movimentos!$F$2:$F$300,Movimentos!$D$2:$D$300,$B38,Movimentos!$E$2:$E$300,"Venda") -> 0
A39: TOTAL | E39: =SUM(E2:E38) -> 6474 | I39: =SUM(I2:I38) -> 120348.5 | K39: =SUM(K2:K38) -> 421

Sheet Movimentos
A1: Data | B1: Hora | C1: Item | D1: Código | E1: Tipo | F1: Quantidade | G1: Saldo após | H1: Observação | I1: Origem
A2: 46283 | B2: 08:00 | C2: Anéis 8126 0,50 | D2: 8126 0,50 | E2: Correção de saldo | F2: 3 | G2: 3 | H2: Contagem física do galpão | I2: Relatório
A3: 46283 | B3: 08:00 | C3: Anéis 9200 STD | D3: 9200 STD | E3: Correção de saldo | F3: 18 | G3: 18 | H3: Contagem física do galpão | I3: Relatório
A4: 46283 | B4: 08:00 | C4: Anéis 9403 STD | D4: 9403 STD | E4: Correção de saldo | F4: 20 | G4: 20 | H4: Contagem física do galpão | I4: Relatório
A5: 46283 | B5: 08:00 | C5: Anel 8126 STD | D5: 8126 STD | E5: Correção de saldo | F5: 1 | G5: 1 | H5: Contagem física do galpão | I5: Relatório
A6: 46283 | B6: 08:00 | C6: Anel SDA 6631 0,50 | D6: 6631 0,50 | E6: Correção de saldo | F6: 130 | G6: 130 | H6: Contagem física do galpão | I6: Relatório
A7: 46283 | B7: 08:00 | C7: Anel SDA 7092 | D7: 7092 | E7: Correção de saldo | F7: 25 | G7: 25 | H7: Contagem física do galpão | I7: Relatório
A8: 46283 | B8: 08:00 | C8: Bronzina de Biela SBB 1035-J 0,25 | D8: 1035-J | E8: Correção de saldo | F8: 24 | G8: 24 | H8: Contagem física do galpão | I8: Relatório
A9: 46283 | B9: 08:00 | C9: Jogo de Anel 7224 0,50 | D9: 7224 0,50 | E9: Correção de saldo | F9: 54 | G9: 54 | H9: Contagem física do galpão | I9: Relatório
A10: 46283 | B10: 08:00 | C10: Jogo de Anel 7224 STD | D10: 7224 STD | E10: Correção de saldo | F10: 43 | G10: 43 | H10: Contagem física do galpão | I10: Relatório
A11: 46283 | B11: 08:00 | C11: Retentor 1135 | D11: 1135 | E11: Correção de saldo | F11: 118 | G11: 118 | H11: Contagem física do galpão | I11: Relatório
A12: 46283 | B12: 08:00 | C12: Retentor 1942 | D12: 1942 | E12: Correção de saldo | F12: 675 | G12: 675 | H12: Contagem física do galpão | I12: Relatório
A13: 46283 | B13: 08:00 | C13: Retentor 2075 | D13: 2075 | E13: Correção de saldo | F13: 124 | G13: 124 | H13: Contagem física do galpão | I13: Relatório
... A142: 46290 | B142: 09:10 | C142: Jogo de Anel 7224 0,50 | D142: 7224 0,50 | E142: Venda | F142: -1 | G142: 51 | H142: Retirada do estoque | I142: Relatório
A143: 46290 | B143: 18:47 | C143: Anéis 8126 0,50 | D143: 8126 0,50 | E143: Entrada | F143: 1 | G143: 1 | I143: App
A144: 46290 | B144: 18:47 | C144: Retentor 5702 | D144: 5702 | E144: Entrada | F144: 3 | G144: 3 | I144: App
