Workbook

Sheet Resumo
A1: Mercado Livre Full — posição de 09/10/2026
A2: Fonte: print do relatório de estoque Full do Mercado Livre + custo e preço de venda líquido do seu catálogo (app Estoque Vivo).
A4: Situação no Mercado Livre | B4: Unidades | C4: Custo (R$) | D4: Receita projetada (R$) | E4: Margem projetada (R$) | F4: O que significa
A5: Aptas para venda | B5: =SUM('Full por SKU'!D2:D32) -> 1902 | C5: =SUMPRODUCT('Full por SKU'!D2:D32,'Full por SKU'!L2:L32) -> 37461 | D5: =SUMPRODUCT('Full por SKU'!D2:D32,'Full por SKU'!M2:M32) -> 59538.78 | E5: =D5-C5 -> 22077.78 | F5: Já estão no Full e à venda.
A6: Temporariamente não aptas | B6: =SUM('Full por SKU'!E2:E32) -> 24 | C6: =SUMPRODUCT('Full por SKU'!E2:E32,'Full por SKU'!L2:L32) -> 1106 | D6: =SUMPRODUCT('Full por SKU'!E2:E32,'Full por SKU'!M2:M32) -> 1547.46 | E6: =D6-C6 -> 441.46 | F6: Extraviadas, em revisão ou de vendas canceladas.
A7: TOTAL NO FULL | B7: =B5+B6 -> 1926 | C7: =C5+C6 -> 38567 | D7: =D5+D6 -> 61086.24 | E7: =E5+E6 -> 22519.24 | F7: Dentro dos galpões do ML.
A8: Entrada pendente (em contagem) | B8: =SUM('Full por SKU'!G2:G32) -> 394 | C8: =SUMPRODUCT('Full por SKU'!G2:G32,'Full por SKU'!L2:L32) -> 27336 | D8: =SUMPRODUCT('Full por SKU'!G2:G32,'Full por SKU'!M2:M32) -> 42100.69 | E8: =D8-C8 -> 14764.69 | F8: Já chegaram ao Full e o ML ainda está conferindo.
A9: Em transferência (a caminho) | B9: =SUM('Full por SKU'!H2:H32) -> 499 | C9: =SUMPRODUCT('Full por SKU'!H2:H32,'Full por SKU'!L2:L32) -> 18884 | D9: =SUMPRODUCT('Full por SKU'!H2:H32,'Full por SKU'!M2:M32) -> 28324.59 | E9: =D9-C9 -> 9440.59 | F9: Envios que saíram do seu galpão e ainda não chegaram ao Full.
A10: Devolvidas pelo comprador | B10: =SUM('Full por SKU'!I2:I32) -> 42 | C10: =SUMPRODUCT('Full por SKU'!I2:I32,'Full por SKU'!L2:L32) -> 1222.5 | D10: =SUMPRODUCT('Full por SKU'!I2:I32,'Full por SKU'!M2:M32) -> 1725.34 | E10: =D10-C10 -> 502.84 | F10: Devoluções voltando ao Full. Podem voltar avariadas: o valor é o máximo.
A11: TOTAL PENDENTE / A CAMINHO | B11: =B8+B9+B10 -> 935 | C11: =C8+C9+C10 -> 47442.5 | D11: =D8+D9+D10 -> 72150.62 | E11: =E8+E9+E10 -> 24708.12 | F11: Ainda não estão à venda.
A12: TOTAL QUE OCUPA ESPAÇO NO FULL | B12: =B7+B11 -> 2861 | C12: =C7+C11 -> 86009.5 | D12: =D7+D11 -> 133236.86 | E12: =E7+E11 -> 47227.36 | F12: É o número que o ML mostra na coluna de espaço ocupado.
A14: Visão da empresa
A15: Onde está | B15: Unidades | C15: Custo (R$) | D15: Receita projetada (R$) | E15: Margem projetada (R$) | F15: Observação
A16: Seu galpão (app Estoque Vivo) | B16: 5258 | C16: 101927 | D16: 159589.3 | E16: =D16-C16 -> 57662.3 | F16: Números do app em 09/10/2026. Os envios em transferência já saíram do galpão no app.
A17: Mercado Livre Full (no Full + a caminho) | B17: =B12 -> 2861 | C17: =C12 -> 86009.5 | D17: =D12 -> 133236.86 | E17: =E12 -> 47227.36 | F17: Total que ocupa espaço no Full, da tabela acima.
A18: TOTAL DA EMPRESA | B18: =B16+B17 -> 8119 | C18: =C16+C17 -> 187936.5 | D18: =D16+D17 -> 292826.16 | E18: =E16+E17 -> 104889.66 | F18: Tudo o que é seu: galpão, Full, a caminho e devoluções.
A20: Como ler
A21: • Receita projetada = unidades × seu preço de venda líquido (o que você recebe por peça, já sem as tarifas do ML). Margem = receita − custo.
A22: • Custo e preço vêm do seu catálogo (células amarelas da aba Full por SKU). Se mudar um valor ali, o resumo recalcula sozinho.
A23: • Não aptas = espaço ocupado − (aptas + entrada pendente + em transferência + devolvidas). O print esconde as colunas de não aptas do ML; a conta fecha com o total de 2.861 unidades do relatório.
A24: • O print não traz vendas dos últimos 30 dias nem urgência de envio. Para ter cobertura em dias, mande o arquivo .xlsx do relatório do ML.

Sheet Full por SKU
A1: SKU no ML | B1: Código | C1: Produto | D1: Aptas para venda | E1: Não aptas | F1: Total no Full | G1: Entrada pendente (em contagem) | H1: Em transferência (a caminho) | I1: Devolvidas pelo comprador | J1: Total pendente / a caminho | K1: Ocupam espaço no Full (ML) | L1: Custo unit. (R$) | M1: Preço venda líquido (R$) | N1: Custo total (R$) | O1: Receita projetada (R$) | P1: Margem projetada (R$) | Q1: No seu galpão (app)
A2: 5801full | B2: 5801 | C2: Retentor Volante Gol Voyage Vw G4 G5 G6 1.0 1.6 8v Fox 5801 | D2: 48 | E2: 5 | F2: =D2+E2 -> 53 | G2: 200 | H2: 13 | I2: 5 | J2: =G2+H2+I2 -> 218 | K2: =F2+J2 -> 271 | L2: 85 | M2: 128.49 | N2: =K2*L2 -> 23035 | O2: =K2*M2 -> 34820.79 | P2: =O2-N2 -> 11785.79 | Q2: 4
A3: 5338full | B3: 5338 | C3: Retentor Traseiro Virabrequim Fiesta Ka Sabó 5338 Zetec | D3: 80 | E3: 1 | F3: =D3+E3 -> 81 | G3: 67 | H3: 163 | I3: 3 | J3: =G3+H3+I3 -> 233 | K3: =F3+J3 -> 314 | L3: 60 | M3: 88.22 | N3: =K3*L3 -> 18840 | O3: =K3*M3 -> 27701.08 | P3: =O3-N3 -> 8861.08 | Q3: 161
A4: 8126full | B4: 8126 STD | C4: Jogo Anel Pistao Std Vw Fox 1.6 8v Ea111 2004 A 2016 | D4: 71 | E4: 0 | F4: =D4+E4 -> 71 | G4: 20 | H4: 33 | I4: 0 | J4: =G4+H4+I4 -> 53 | K4: =F4+J4 -> 124 | L4: 75 | M4: 129.97 | N4: =K4*L4 -> 9300 | O4: =K4*M4 -> 16116.28 | P4: =O4-N4 -> 6816.28 | Q4: 233
A5: 7224STDfull | B5: 7224 STD | C5: Jogo Anéis Motor Vw 1.0 Fox 8v At Ea111 2004 A 2010 7224 Std | D5: 7 | E5: 0 | F5: =D5+E5 -> 7 | G5: 50 | H5: 0 | I5: 0 | J5: =G5+H5+I5 -> 50 | K5: =F5+J5 -> 57 | L5: 75 | M5: 125.87 | N5: =K5*L5 -> 4275 | O5: =K5*M5 -> 7174.59 | P5: =O5-N5 -> 2899.59 | Q5: 9
A6: 5772strada | B6: 5772 | C6: Retentor Traseiro Virabrequim Sabo Fiat Strada Fire 1.4 8v | D6: 22 | E6: 2 | F6: =D6+E6 -> 24 | G6: 0 | H6: 60 | I6: 0 | J6: =G6+H6+I6 -> 60 | K6: =F6+J6 -> 84 | L6: 50 | M6: 65.84 | N6: =K6*L6 -> 4200 | O6: =K6*M6 -> 5530.56 | P6: =O6-N6 -> 1330.56 | Q6: 18
A7: 7092 | B7: 7092 | C7: Jogo Aneis Pistao Std Chevrolet Corsa 1.0 8v De 1994 A 2006 | D7: 44 | E7: 0 | F7: =D7+E7 -> 44 | G7: 0 | H7: 0 | I7: 0 | J7: =G7+H7+I7 -> 0 | K7: =F7+J7 -> 44 | L7: 75 | M7: 126.89 | N7: =K7*L7 -> 3300 | O7: =K7*M7 -> 5583.16 | P7: =O7-N7 -> 2283.16 | Q7: 95
A8: 9203full | B8: 9203 | C8: Vedadores Haste De Válvula Gol 1.0/1.6 Motor Ea111 6mm 09203 | D8: 249 | E8: 1 | F8: =D8+E8 -> 250 | G8: 0 | H8: 71 | I8: 9 | J8: =G8+H8+I8 -> 80 | K8: =F8+J8 -> 330 | L8: 9 | M8: 11.25 | N8: =K8*L8 -> 2970 | O8: =K8*M8 -> 3712.5 | P8: =O8-N8 -> 742.5 | Q8: 208
A9: 2178full | B9: 2178 | C9: Retentor Do Comando Válvulas Astra Celta Corsa Meriva Vectra | D9: 301 | E9: 4 | F9: =D9+E9 -> 305 | G9: 2 | H9: 41 | I9: 9 | J9: =G9+H9+I9 -> 52 | K9: =F9+J9 -> 357 | L9: 8 | M9: 10.55 | N9: =K9*L9 -> 2856 | O9: =K9*M9 -> 3766.35 | P9: =O9-N9 -> 910.35 | Q9: 103
A10: 5159full | B10: 5159 | C10: Retentor Eixo Comando Gol Power Motor Ea111 8 Válvulas 5159 | D10: 272 | E10: 0 | F10: =D10+E10 -> 272 | G10: 0 | H10: 0 | I10: 0 | J10: =G10+H10+I10 -> 0 | K10: =F10+J10 -> 272 | L10: 8 | M10: 11.78 | N10: =K10*L10 -> 2176 | O10: =K10*M10 -> 3204.16 | P10: =O10-N10 -> 1028.16 | Q10: 881
A11: 5601full | B11: 5601 | C11: Retentor Volante Clio/sandero/logan/megane/ 1.6 8/16v 5601 | D11: 34 | E11: 0 | F11: =D11+E11 -> 34 | G11: 30 | H11: 8 | I11: 0 | J11: =G11+H11+I11 -> 38 | K11: =F11+J11 -> 72 | L11: 25 | M11: 37.34 | N11: =K11*L11 -> 1800 | O11: =K11*M11 -> 2688.48 | P11: =O11-N11 -> 888.48 | Q11: 84
A12: 5699full | B12: 5699 | C12: Retentor Do Volante Liso Vw Fox 1.0 8v At Power 2001 A 2007 | D12: 17 | E12: 0 | F12: =D12+E12 -> 17 | G12: 0 | H12: 1 | I12: 0 | J12: =G12+H12+I12 -> 1 | K12: =F12+J12 -> 18 | L12: 95 | M12: 168.08 | N12: =K12*L12 -> 1710 | O12: =K12*M12 -> 3025.44 | P12: =O12-N12 -> 1315.44 | Q12: 24
A13: 6631050full | B13: 6631 0,50 | C13: Jogo Aneis Motor Original 050 Gm Monza 2.0 8v 1986 Ate 1997 | D13: 17 | E13: 0 | F13: =D13+E13 -> 17 | G13: 0 | H13: 2 | I13: 0 | J13: =G13+H13+I13 -> 2 | K13: =F13+J13 -> 19 | L13: 75 | M13: 135.84 | N13: =K13*L13 -> 1425 | O13: =K13*M13 -> 2580.96 | P13: =O13-N13 -> 1155.96 | Q13: 79
... A32: 5702full | B32: 5702 | C32: Retentor Virabrequim Polia Zetec Rocam 1.0 / 1.4 / 1.6 05702 | D32: 0 | E32: 0 | F32: =D32+E32 -> 0 | G32: 0 | H32: 0 | I32: 0 | J32: =G32+H32+I32 -> 0 | K32: =F32+J32 -> 0 | L32: 50 | M32: 50.33 | N32: =K32*L32 -> 0 | O32: =K32*M32 -> 0 | P32: =O32-N32 -> 0 | Q32: 0
A33: TOTAL | D33: =SUM(D2:D32) -> 1902 | E33: =SUM(E2:E32) -> 24 | F33: =SUM(F2:F32) -> 1926 | G33: =SUM(G2:G32) -> 394 | H33: =SUM(H2:H32) -> 499 | I33: =SUM(I2:I32) -> 42 | J33: =SUM(J2:J32) -> 935 | K33: =SUM(K2:K32) -> 2861 | N33: =SUM(N2:N32) -> 86009.5 | O33: =SUM(O2:O32) -> 133236.86 | P33: =SUM(P2:P32) -> 47227.36 | Q33: =SUM(Q2:Q32) -> 5045
