Workbook

Sheet Resumo
A1: Mercado Livre Full — posição de 25/09/2026
A2: Fonte: relatório de estoque Full do Mercado Livre + custo e preço de venda líquido do seu catálogo (app Estoque Vivo).
A4: Situação no Mercado Livre | B4: Unidades | C4: Custo parado (R$) | D4: Receita projetada (R$) | E4: Margem projetada (R$) | F4: O que significa
A5: Aptas para venda | B5: =SUM('Full por SKU'!D2:D32) -> 1587 | C5: =SUMPRODUCT('Full por SKU'!D2:D32,'Full por SKU'!J2:J32) -> 37214.5 | D5: =SUMPRODUCT('Full por SKU'!D2:D32,'Full por SKU'!K2:K32) -> 63694.19 | E5: =D5-C5 -> 26479.69 | F5: Já estão no Full e à venda.
A6: Em transferência entre galpões do ML | B6: =SUM('Full por SKU'!E2:E32) -> 72 | C6: =SUMPRODUCT('Full por SKU'!E2:E32,'Full por SKU'!J2:J32) -> 1570.5 | D6: =SUMPRODUCT('Full por SKU'!E2:E32,'Full por SKU'!K2:K32) -> 2760.32 | E6: =D6-C6 -> 1189.82 | F6: Dentro do Full, mudando de um galpão do ML para outro.
A7: Temporariamente não aptas | B7: =SUM('Full por SKU'!F2:F32) -> 1 | C7: =SUMPRODUCT('Full por SKU'!F2:F32,'Full por SKU'!J2:J32) -> 7 | D7: =SUMPRODUCT('Full por SKU'!F2:F32,'Full por SKU'!K2:K32) -> 10.3 | E7: =D7-C7 -> 3.3 | F7: Extraviadas, em revisão ou de vendas canceladas.
A8: TOTAL NO FULL | B8: =SUM(B5:B7) -> 1660 | C8: =SUM(C5:C7) -> 38792 | D8: =SUM(D5:D7) -> 66464.81 | E8: =SUM(E5:E7) -> 27672.81 | F8: Dinheiro parado dentro dos galpões do Mercado Livre.
A9: A caminho do Full (entrada pendente) | B9: =SUM('Full por SKU'!H2:H32) -> 648 | C9: =SUMPRODUCT('Full por SKU'!H2:H32,'Full por SKU'!J2:J32) -> 23450 | D9: =SUMPRODUCT('Full por SKU'!H2:H32,'Full por SKU'!K2:K32) -> 38001.45 | E9: =D9-C9 -> 14551.45 | F9: Envios que o ML ainda não recebeu. Saíram do galpão antes da contagem de 18/09, então o app já não conta essas peças.
A10: Devoluções voltando ao Full | B10: =SUM('Full por SKU'!I2:I32) -> 34 | C10: =SUMPRODUCT('Full por SKU'!I2:I32,'Full por SKU'!J2:J32) -> 1480 | D10: =SUMPRODUCT('Full por SKU'!I2:I32,'Full por SKU'!K2:K32) -> 2259.47 | E10: =D10-C10 -> 779.47 | F10: Vendas devolvidas a caminho do Full. Podem voltar avariadas: o valor é o máximo.
A12: Visão da empresa
A13: Onde está | B13: Unidades | C13: Custo parado (R$) | D13: Receita projetada (R$) | E13: Margem projetada (R$) | F13: Observação
A14: Seu galpão (app Estoque Vivo) | B14: 6474 | C14: 120348.5 | D14: 203232.24 | E14: =D14-C14 -> 82883.74 | F14: Números do app em 25/09/2026. Sem preço de venda: 2900, 8566 STD, 9403 STD.
A15: Dentro do Full | B15: =B8 -> 1660 | C15: =C8 -> 38792 | D15: =D8 -> 66464.81 | E15: =E8 -> 27672.81 | F15: Total no Full, da tabela acima.
A16: A caminho do Full | B16: =B9 -> 648 | C16: =C9 -> 23450 | D16: =D9 -> 38001.45 | E16: =E9 -> 14551.45
A17: Devoluções voltando ao Full | B17: =B10 -> 34 | C17: =C10 -> 1480 | D17: =D10 -> 2259.47 | E17: =E10 -> 779.47
A18: TOTAL DA EMPRESA | B18: =SUM(B14:B17) -> 8816 | C18: =SUM(C14:C17) -> 184070.5 | D18: =SUM(D14:D17) -> 309957.97 | E18: =SUM(E14:E17) -> 125887.47 | F18: Tudo o que é seu: galpão, Full, a caminho e devoluções.
A20: Referência do Mercado Livre — últimos 30 dias
A21: Vendas no ML (R$, bruto) | B21: =SUM('Full por SKU'!P2:P32) -> 177383.28 | F21: Valor de venda registrado pelo ML, antes das tarifas.
A22: Unidades vendidas | B22: =SUM('Full por SKU'!O2:O32) -> 2563
A23: Ticket médio no ML (R$) | B23: =IF(B22>0,B21/B22,0) -> 69.209239 | F23: Preço médio de venda no ML por unidade.
A24: De cada R$ 100 vendidos no ML, você recebe | B24: =IF(B21>0,SUMPRODUCT('Full por SKU'!O2:O32,'Full por SKU'!K2:K32)/B21*100,0) -> 72.065693 | F24: Estimativa: unidades vendidas × seu preço líquido ÷ vendas brutas. O resto são tarifas e frete do ML.
A25: Estoque do Full pelo ticket médio do ML (R$, bruto) | B25: =SUMPRODUCT('Full por SKU'!G2:G32,'Full por SKU'!Q2:Q32) -> 97148.16 | F25: Quanto o estoque do Full faturaria no ML pelo preço médio do último mês, antes das tarifas.
A26: Cobertura média do Full (dias) | B26: =IF(B22>0,ROUND((B5+B6)/(B22/30),1),0) -> 19.4 | F26: Quantos dias o estoque do Full dura no ritmo de venda atual.
A28: Alertas de reposição (aba Full por SKU)
A29: Urgência "Urgente" | B29: =COUNTIF('Full por SKU'!S2:S32,"Urgente") -> 1 | F29: Status que o próprio ML calcula para cada anúncio.
A30: Urgência "Esta semana" | B30: =COUNTIF('Full por SKU'!S2:S32,"Esta semana") -> 3
A31: Urgência "Próxima semana" | B31: =COUNTIF('Full por SKU'!S2:S32,"Próxima semana") -> 2
A32: Estoque "Excedente" no Full | B32: =COUNTIF('Full por SKU'!S2:S32,"Excedente") -> 2 | F32: O ML considera que há estoque demais. Pode gerar tarifa de armazenagem.
A33: SKUs com menos de 7 dias de cobertura | B33: =COUNTIF('Full por SKU'!R2:R32,"<7") -> 4
A35: Como ler
A36: • Receita projetada = unidades × seu preço de venda líquido (o que você recebe por peça, já sem as tarifas do ML). Custo parado = unidades × custo. Margem = receita − custo.
A37: • Custo e preço vêm do seu catálogo (células amarelas da aba Full por SKU). Se mudar um valor ali, o resumo recalcula sozinho.
A38: • A caminho do Full: saíram do galpão antes da contagem de 18/09. O 5801 e o 5245 confirmam isso: o galpão nunca teve essas quantidades depois da contagem. Por isso somam no total da empresa sem contar duas vezes.
A39: • Devoluções: o ML conta 682 unidades em entrada pendente na coluna de espaço ocupado e 648 na coluna "a caminho". A diferença (34) são devoluções de clientes voltando ao Full.
A40: • Cobertura = (aptas + em transferência) ÷ venda diária dos últimos 30 dias. Vermelho abaixo de 7 dias, laranja acima de 90.

Sheet Full por SKU
A1: SKU no ML | B1: Código | C1: Produto | D1: Aptas para venda | E1: Em transferência | F1: Não aptas | G1: Total no Full | H1: A caminho do Full | I1: Devoluções voltando | J1: Custo unit. (R$) | K1: Preço venda líquido (R$) | L1: Custo parado no Full (R$) | M1: Receita projetada (R$) | N1: Margem projetada (R$) | O1: Vendidas 30 dias | P1: Vendas 30 dias no ML (R$) | Q1: Ticket médio no ML (R$) | R1: Cobertura (dias) | S1: Urgência de envio (ML) | T1: ML sugere enviar | U1: No seu galpão (app)
A2: 8126full | B2: 8126 STD | C2: Jogo Anel Pistao Std Vw Fox 1.6 8v Ea111 2004 A 2016 | D2: 105 | E2: 2 | F2: 0 | G2: =D2+E2+F2 -> 107 | H2: 0 | I2: 0 | J2: 75 | K2: 142.25 | L2: =G2*J2 -> 8025 | M2: =G2*K2 -> 15220.75 | N2: =M2-L2 -> 7195.75 | O2: 45 | P2: 8237.93 | Q2: =IF(O2>0,P2/O2,0) -> 183.06511 | R2: =IF(O2>0,ROUND((D2+E2)/(O2/30),1),"") -> 71.3 | S2: Sem urgência | T2: 0 | U2: 289
A3: 5338full | B3: 5338 | C3: Retentor Traseiro Virabrequim Fiesta Ka Sabó 5338 Zetec | D3: 82 | E3: 5 | F3: 0 | G3: =D3+E3+F3 -> 87 | H3: 60 | I3: 3 | J3: 60 | K3: 88.68 | L3: =G3*J3 -> 5220 | M3: =G3*K3 -> 7715.16 | N3: =M3-L3 -> 2495.16 | O3: 129 | P3: 15809.42 | Q3: =IF(O3>0,P3/O3,0) -> 122.55364 | R3: =IF(O3>0,ROUND((D3+E3)/(O3/30),1),"") -> 20.2 | S3: Sem urgência | T3: 0 | U3: 122
A4: 5245full | B4: 5245 | C4: Retentor Volante Traseiro Palio Fiat Fire 1.0/1.3l 8v Sabó | D4: 83 | E4: 1 | F4: 0 | G4: =D4+E4+F4 -> 84 | H4: 63 | I4: 9 | J4: 55 | K4: 68.35 | L4: =G4*J4 -> 4620 | M4: =G4*K4 -> 5741.4 | N4: =M4-L4 -> 1121.4 | O4: 347 | P4: 32636.71 | Q4: =IF(O4>0,P4/O4,0) -> 94.053919 | R4: =IF(O4>0,ROUND((D4+E4)/(O4/30),1),"") -> 7.3 | S4: Esta semana | T4: 0 | U4: 50
A5: 7092 | B5: 7092 | C5: Jogo Aneis Pistao Std Chevrolet Corsa 1.0 8v De 1994 A 2006 | D5: 37 | E5: 0 | F5: 0 | G5: =D5+E5+F5 -> 37 | H5: 0 | I5: 0 | J5: 75 | K5: 127.94 | L5: =G5*J5 -> 2775 | M5: =G5*K5 -> 4733.78 | N5: =M5-L5 -> 1958.78 | O5: 30 | P5: 4641.9 | Q5: =IF(O5>0,P5/O5,0) -> 154.73 | R5: =IF(O5>0,ROUND((D5+E5)/(O5/30),1),"") -> 37 | S5: Sem urgência | T5: 0 | U5: 22
A6: 5159full | B6: 5159 | C6: Retentor Eixo Comando Gol Power Motor Ea111 8 Válvulas 5159 | D6: 281 | E6: 0 | F6: 0 | G6: =D6+E6+F6 -> 281 | H6: 0 | I6: 0 | J6: 8 | K6: 13.36 | L6: =G6*J6 -> 2248 | M6: =G6*K6 -> 3754.16 | N6: =M6-L6 -> 1506.16 | O6: 72 | P6: 2047.09 | Q6: =IF(O6>0,P6/O6,0) -> 28.431806 | R6: =IF(O6>0,ROUND((D6+E6)/(O6/30),1),"") -> 117.1 | S6: Excedente | T6: 0 | U6: 892
A7: 5699full | B7: 5699 | C7: Retentor Do Volante Liso Vw Fox 1.0 8v At Power 2001 A 2007 | D7: 20 | E7: 3 | F7: 0 | G7: =D7+E7+F7 -> 23 | H7: 0 | I7: 0 | J7: 95 | K7: 231.86 | L7: =G7*J7 -> 2185 | M7: =G7*K7 -> 5332.78 | N7: =M7-L7 -> 3147.78 | O7: 17 | P7: 3812.34 | Q7: =IF(O7>0,P7/O7,0) -> 224.25529 | R7: =IF(O7>0,ROUND((D7+E7)/(O7/30),1),"") -> 40.6 | S7: Sem urgência | T7: 0 | U7: 27
A8: 9203full | B8: 9203 | C8: Vedadores Haste De Válvula Gol 1.0/1.6 Motor Ea111 6mm 09203 | D8: 183 | E8: 18 | F8: 0 | G8: =D8+E8+F8 -> 201 | H8: 0 | I8: 1 | J8: 9 | K8: 13.36 | L8: =G8*J8 -> 1809 | M8: =G8*K8 -> 2685.36 | N8: =M8-L8 -> 876.36 | O8: 292 | P8: 7818.31 | Q8: =IF(O8>0,P8/O8,0) -> 26.775034 | R8: =IF(O8>0,ROUND((D8+E8)/(O8/30),1),"") -> 20.7 | S8: Sem urgência | T8: 0 | U8: 318
A9: 5772strada | B9: 5772 | C9: Retentor Traseiro Virabrequim Sabo Fiat Strada Fire 1.4 8v | D9: 26 | E9: 4 | F9: 0 | G9: =D9+E9+F9 -> 30 | H9: 0 | I9: 0 | J9: 50 | K9: 70.29 | L9: =G9*J9 -> 1500 | M9: =G9*K9 -> 2108.7 | N9: =M9-L9 -> 608.7 | O9: 69 | P9: 6569.76 | Q9: =IF(O9>0,P9/O9,0) -> 95.213913 | R9: =IF(O9>0,ROUND((D9+E9)/(O9/30),1),"") -> 13 | S9: Próxima semana | T9: 49 | U9: 148
A10: 6631050full | B10: 6631 0,50 | C10: Jogo Aneis Motor Original 050 Gm Monza 2.0 8v 1986 Ate 1997 | D10: 20 | E10: 0 | F10: 0 | G10: =D10+E10+F10 -> 20 | H10: 0 | I10: 0 | J10: 75 | K10: 148.56 | L10: =G10*J10 -> 1500 | M10: =G10*K10 -> 2971.2 | N10: =M10-L10 -> 1471.2 | O10: 33 | P10: 6010.5 | Q10: =IF(O10>0,P10/O10,0) -> 182.13636 | R10: =IF(O10>0,ROUND((D10+E10)/(O10/30),1),"") -> 18.2 | S10: Sem urgência | T10: 0 | U10: 99
A11: 1942full | B11: 1942 | C11: Retentor Comando Polia Vira Motor Ap 1.6 1.8 2.0 1942 | D11: 165 | E11: 3 | F11: 0 | G11: =D11+E11+F11 -> 168 | H11: 0 | I11: 2 | J11: 8 | K11: 12.32 | L11: =G11*J11 -> 1344 | M11: =G11*K11 -> 2069.76 | N11: =M11-L11 -> 725.76 | O11: 78 | P11: 2290.16 | Q11: =IF(O11>0,P11/O11,0) -> 29.361026 | R11: =IF(O11>0,ROUND((D11+E11)/(O11/30),1),"") -> 64.6 | S11: Sem urgência | T11: 0 | U11: 558
A12: 2178full | B12: 2178 | C12: Retentor Do Comando Válvulas Astra Celta Corsa Meriva Vectra | D12: 146 | E12: 17 | F12: 0 | G12: =D12+E12+F12 -> 163 | H12: 0 | I12: 4 | J12: 8 | K12: 11.18 | L12: =G12*J12 -> 1304 | M12: =G12*K12 -> 1822.34 | N12: =M12-L12 -> 518.34 | O12: 448 | P12: 11767.88 | Q12: =IF(O12>0,P12/O12,0) -> 26.267589 | R12: =IF(O12>0,ROUND((D12+E12)/(O12/30),1),"") -> 10.9 | S12: Sem urgência | T12: 0 | U12: 311
A13: 5502 | B13: 5502 | C13: Retentor Virabrequim Traseiro Gol Parati 1.0 8v 16v Motor At | D13: 13 | E13: 0 | F13: 0 | G13: =D13+E13+F13 -> 13 | H13: 0 | I13: 0 | J13: 70 | K13: 119.3 | L13: =G13*J13 -> 910 | M13: =G13*K13 -> 1550.9 | N13: =M13-L13 -> 640.9 | O13: 9 | P13: 1418.72 | Q13: =IF(O13>0,P13/O13,0) -> 157.63556 | R13: =IF(O13>0,ROUND((D13+E13)/(O13/30),1),"") -> 43.3 | S13: Sem urgência | T13: 0 | U13: 44
... A32: 5702full | B32: 5702 | C32: Retentor Virabrequim Polia Zetec Rocam 1.0 / 1.4 / 1.6 05702 | D32: 0 | E32: 0 | F32: 0 | G32: =D32+E32+F32 -> 0 | H32: 0 | I32: 0 | J32: 50 | K32: 57.36 | L32: =G32*J32 -> 0 | M32: =G32*K32 -> 0 | N32: =M32-L32 -> 0 | O32: 3 | P32: 239.7 | Q32: =IF(O32>0,P32/O32,0) -> 79.9 | R32: =IF(O32>0,ROUND((D32+E32)/(O32/30),1),"") -> 0 | S32: Urgente | T32: 35 | U32: 3
A33: TOTAL | D33: =SUM(D2:D32) -> 1587 | E33: =SUM(E2:E32) -> 72 | F33: =SUM(F2:F32) -> 1 | G33: =SUM(G2:G32) -> 1660 | H33: =SUM(H2:H32) -> 648 | I33: =SUM(I2:I32) -> 34 | L33: =SUM(L2:L32) -> 38792 | M33: =SUM(M2:M32) -> 66464.81 | N33: =SUM(N2:N32) -> 27672.81 | O33: =SUM(O2:O32) -> 2563 | P33: =SUM(P2:P32) -> 177383.28 | Q33: =IF(O33>0,P33/O33,0) -> 69.209239 | R33: =IF(O33>0,ROUND((D33+E33)/(O33/30),1),"") -> 19.4 | T33: =SUM(T2:T32) -> 141 | U33: =SUM(U2:U32) -> 6325
