Workbook

Sheet Resumo
A1: Seu galpão — projeção de 25/09/2026
A2: Fonte: planilha de estoque do galpão + relatório de estoque Full do Mercado Livre.
A4: Categoria | B4: Unidades | C4: Custo parado (R$) | D4: Receita projetada (R$) | E4: Margem projetada (R$) | F4: Margem (%) | G4: Observação
A5: Anéis | B5: =SUMIFS('Galpão por SKU'!D2:D38,'Galpão por SKU'!C2:C38,A5,'Galpão por SKU'!F2:F38,">0") -> 418 | C5: =SUMIFS('Galpão por SKU'!G2:G38,'Galpão por SKU'!C2:C38,A5,'Galpão por SKU'!F2:F38,">0") -> 31350 | D5: =SUMIFS('Galpão por SKU'!H2:H38,'Galpão por SKU'!C2:C38,A5) -> 59869.48 | E5: =D5-C5 -> 28519.48 | F5: =IF(D5>0,E5/D5,"") -> 0.47636091
A6: Bronzina | B6: =SUMIFS('Galpão por SKU'!D2:D38,'Galpão por SKU'!C2:C38,A6,'Galpão por SKU'!F2:F38,">0") -> 22 | C6: =SUMIFS('Galpão por SKU'!G2:G38,'Galpão por SKU'!C2:C38,A6,'Galpão por SKU'!F2:F38,">0") -> 704 | D6: =SUMIFS('Galpão por SKU'!H2:H38,'Galpão por SKU'!C2:C38,A6) -> 1523.5 | E6: =D6-C6 -> 819.5 | F6: =IF(D6>0,E6/D6,"") -> 0.53790614
A7: Jogo de Anel | B7: =SUMIFS('Galpão por SKU'!D2:D38,'Galpão por SKU'!C2:C38,A7,'Galpão por SKU'!F2:F38,">0") -> 86 | C7: =SUMIFS('Galpão por SKU'!G2:G38,'Galpão por SKU'!C2:C38,A7,'Galpão por SKU'!F2:F38,">0") -> 6450 | D7: =SUMIFS('Galpão por SKU'!H2:H38,'Galpão por SKU'!C2:C38,A7) -> 13238.4 | E7: =D7-C7 -> 6788.4 | F7: =IF(D7>0,E7/D7,"") -> 0.512781
A8: Retentor | B8: =SUMIFS('Galpão por SKU'!D2:D38,'Galpão por SKU'!C2:C38,A8,'Galpão por SKU'!F2:F38,">0") -> 5540 | C8: =SUMIFS('Galpão por SKU'!G2:G38,'Galpão por SKU'!C2:C38,A8,'Galpão por SKU'!F2:F38,">0") -> 72232.5 | D8: =SUMIFS('Galpão por SKU'!H2:H38,'Galpão por SKU'!C2:C38,A8) -> 124352.38 | E8: =D8-C8 -> 52119.88 | F8: =IF(D8>0,E8/D8,"") -> 0.41913054
A9: Vedador | B9: =SUMIFS('Galpão por SKU'!D2:D38,'Galpão por SKU'!C2:C38,A9,'Galpão por SKU'!F2:F38,">0") -> 318 | C9: =SUMIFS('Galpão por SKU'!G2:G38,'Galpão por SKU'!C2:C38,A9,'Galpão por SKU'!F2:F38,">0") -> 2862 | D9: =SUMIFS('Galpão por SKU'!H2:H38,'Galpão por SKU'!C2:C38,A9) -> 4248.48 | E9: =D9-C9 -> 1386.48 | F9: =IF(D9>0,E9/D9,"") -> 0.32634731
A10: SUBTOTAL — ITENS COM PREÇO | B10: =SUM(B5:B9) -> 6384 | C10: =SUM(C5:C9) -> 113598.5 | D10: =SUM(D5:D9) -> 203232.24 | E10: =D10-C10 -> 89633.74 | F10: =IF(D10>0,E10/D10,"") -> 0.44104095
A11: Sem preço de venda | B11: =SUM('Galpão por SKU'!D2:D38)-B10 -> 90 | C11: =SUM('Galpão por SKU'!G2:G38)-C10 -> 6750 | D11: 0 | G11: 2900, 8566 STD, 9403 STD: entram no custo, mas não na receita, até ter preço de venda.
A12: TOTAL DO GALPÃO | B12: =SUM('Galpão por SKU'!D2:D38) -> 6474 | C12: =SUM('Galpão por SKU'!G2:G38) -> 120348.5 | D12: =SUM('Galpão por SKU'!H2:H38) -> 203232.24 | E12: =D12-C12 -> 82883.74 | F12: =IF(D12>0,E12/D12,"") -> 0.40782771 | G12: A margem total desconta o custo dos itens sem preço de venda.
A14: Visão da empresa (galpão + Mercado Livre Full)
A15: Onde está | B15: Unidades | C15: Custo parado (R$) | D15: Receita projetada (R$) | E15: Margem projetada (R$) | F15: Margem (%) | G15: Observação
A16: Seu galpão | B16: =B12 -> 6474 | C16: =C12 -> 120348.5 | D16: =D12 -> 203232.24 | E16: =E12 -> 82883.74 | F16: =F12 -> 0.40782771
A17: Dentro do Full | B17: =SUM('Galpão por SKU'!L2:L38) -> 1660 | C17: =SUMPRODUCT('Galpão por SKU'!L2:L38,'Galpão por SKU'!E2:E38) -> 38792 | D17: =SUMPRODUCT('Galpão por SKU'!L2:L38,'Galpão por SKU'!F2:F38) -> 66464.81 | E17: =D17-C17 -> 27672.81 | F17: =IF(D17>0,E17/D17,"") -> 0.4163528 | G17: Aptas, em transferência entre galpões do ML e não aptas.
A18: A caminho do Full | B18: =SUM('Galpão por SKU'!M2:M38) -> 648 | C18: =SUMPRODUCT('Galpão por SKU'!M2:M38,'Galpão por SKU'!E2:E38) -> 23450 | D18: =SUMPRODUCT('Galpão por SKU'!M2:M38,'Galpão por SKU'!F2:F38) -> 38001.45 | E18: =D18-C18 -> 14551.45 | F18: =IF(D18>0,E18/D18,"") -> 0.38291828 | G18: Saíram do galpão antes da contagem de 18/09.
A19: Devoluções voltando ao Full | B19: =SUM('Galpão por SKU'!N2:N38) -> 34 | C19: =SUMPRODUCT('Galpão por SKU'!N2:N38,'Galpão por SKU'!E2:E38) -> 1480 | D19: =SUMPRODUCT('Galpão por SKU'!N2:N38,'Galpão por SKU'!F2:F38) -> 2259.47 | E19: =D19-C19 -> 779.47 | F19: =IF(D19>0,E19/D19,"") -> 0.34497913 | G19: Podem voltar avariadas: o valor é o máximo.
A20: TOTAL DA EMPRESA | B20: =SUM(B16:B19) -> 8816 | C20: =SUM(C16:C19) -> 184070.5 | D20: =SUM(D16:D19) -> 309957.97 | E20: =D20-C20 -> 125887.47 | F20: =IF(D20>0,E20/D20,"") -> 0.40614368 | G20: Mesmos números da planilha do Full.
A22: Giro — quanto tempo o estoque dura
A23: Indicador | B23: SKUs | C23: Custo parado no galpão (R$) | G23: Observação
A24: Mais de 6 meses de estoque | B24: =COUNTIF('Galpão por SKU'!Q2:Q38,">6") -> 12 | C24: =SUMIFS('Galpão por SKU'!G2:G38,'Galpão por SKU'!Q2:Q38,">6") -> 57487.5 | G24: Somando galpão, Full, a caminho e devoluções, no ritmo de venda do ML dos últimos 30 dias.
A25: Mais de 12 meses de estoque | B25: =COUNTIF('Galpão por SKU'!Q2:Q38,">12") -> 5 | C25: =SUMIFS('Galpão por SKU'!G2:G38,'Galpão por SKU'!Q2:Q38,">12") -> 16053
A26: Sem venda no ML nos últimos 30 dias | B26: =COUNTIF('Galpão por SKU'!P2:P38,0) -> 6 | C26: =SUMIFS('Galpão por SKU'!G2:G38,'Galpão por SKU'!P2:P38,0) -> 11175 | G26: Não têm anúncio no Full. Podem estar vendendo por outros canais.
A28: Como ler
A29: • Custo parado = quantidade × custo. Receita projetada = quantidade × seu preço de venda líquido (o que você recebe por peça, já sem as tarifas do ML). Margem = receita − custo.
A30: • Custo e preço vêm da sua planilha (células amarelas da aba Galpão por SKU). Se mudar um valor ali, tudo recalcula.
A31: • No Full, a caminho e devoluções vêm do relatório do Mercado Livre de 25/09/2026, os mesmos números da planilha do Full.
A32: • Meses de estoque = total da empresa ÷ unidades vendidas no ML nos últimos 30 dias. Não conta vendas feitas direto do galpão (Shopee, balcão): itens que também vendem por fora giram mais rápido do que aparece. Laranja acima de 6 meses, vermelho acima de 12.

Sheet Galpão por SKU
A1: Item | B1: Código | C1: Categoria | D1: Quantidade no galpão | E1: Custo unit. (R$) | F1: Preço venda líquido (R$) | G1: Custo parado (R$) | H1: Receita projetada (R$) | I1: Margem projetada (R$) | J1: Margem (%) | K1: % do dinheiro parado no galpão | L1: No Full | M1: A caminho do Full | N1: Devoluções voltando | O1: Total da empresa | P1: Vendidas 30 dias no ML | Q1: Meses de estoque
A2: Anel 8126 STD | B2: 8126 STD | C2: Anéis | D2: 289 | E2: 75 | F2: 142.25 | G2: =D2*E2 -> 21675 | H2: =D2*F2 -> 41110.25 | I2: =IF(F2>0,H2-G2,"") -> 19435.25 | J2: =IF(H2>0,I2/H2,"") -> 0.47275923 | K2: =IF(G$39>0,G2/G$39,0) -> 0.18010195 | L2: 107 | M2: 0 | N2: 0 | O2: =D2+L2+M2+N2 -> 396 | P2: 45 | Q2: =IF(P2>0,ROUND(O2/P2,1),"") -> 8.8
A3: Anel SDA 6631 0,50 | B3: 6631 0,50 | C3: Anéis | D3: 99 | E3: 75 | F3: 148.56 | G3: =D3*E3 -> 7425 | H3: =D3*F3 -> 14707.44 | I3: =IF(F3>0,H3-G3,"") -> 7282.44 | J3: =IF(H3>0,I3/H3,"") -> 0.49515347 | K3: =IF(G$39>0,G3/G$39,0) -> 0.061695825 | L3: 20 | M3: 0 | N3: 0 | O3: =D3+L3+M3+N3 -> 119 | P3: 33 | Q3: =IF(P3>0,ROUND(O3/P3,1),"") -> 3.6
A4: Retentor 5772 | B4: 5772 | C4: Retentor | D4: 148 | E4: 50 | F4: 70.29 | G4: =D4*E4 -> 7400 | H4: =D4*F4 -> 10402.92 | I4: =IF(F4>0,H4-G4,"") -> 3002.92 | J4: =IF(H4>0,I4/H4,"") -> 0.28866126 | K4: =IF(G$39>0,G4/G$39,0) -> 0.061488095 | L4: 30 | M4: 0 | N4: 0 | O4: =D4+L4+M4+N4 -> 178 | P4: 69 | Q4: =IF(P4>0,ROUND(O4/P4,1),"") -> 2.6
A5: Retentor 5338 | B5: 5338 | C5: Retentor | D5: 122 | E5: 60 | F5: 88.68 | G5: =D5*E5 -> 7320 | H5: =D5*F5 -> 10818.96 | I5: =IF(F5>0,H5-G5,"") -> 3498.96 | J5: =IF(H5>0,I5/H5,"") -> 0.32341001 | K5: =IF(G$39>0,G5/G$39,0) -> 0.060823359 | L5: 87 | M5: 60 | N5: 3 | O5: =D5+L5+M5+N5 -> 272 | P5: 129 | Q5: =IF(P5>0,ROUND(O5/P5,1),"") -> 2.1
A6: Retentor 5159 | B6: 5159 | C6: Retentor | D6: 892 | E6: 8 | F6: 13.36 | G6: =D6*E6 -> 7136 | H6: =D6*F6 -> 11917.12 | I6: =IF(F6>0,H6-G6,"") -> 4781.12 | J6: =IF(H6>0,I6/H6,"") -> 0.4011976 | K6: =IF(G$39>0,G6/G$39,0) -> 0.059294466 | L6: 281 | M6: 0 | N6: 0 | O6: =D6+L6+M6+N6 -> 1173 | P6: 72 | Q6: =IF(P6>0,ROUND(O6/P6,1),"") -> 16.3
A7: Retentor 2525 | B7: 2525 | C7: Retentor | D7: 599 | E7: 8 | F7: 13.23 | G7: =D7*E7 -> 4792 | H7: =D7*F7 -> 7924.77 | I7: =IF(F7>0,H7-G7,"") -> 3132.77 | J7: =IF(H7>0,I7/H7,"") -> 0.39531368 | K7: =IF(G$39>0,G7/G$39,0) -> 0.039817696 | L7: 30 | M7: 80 | N7: 1 | O7: =D7+L7+M7+N7 -> 710 | P7: 78 | Q7: =IF(P7>0,ROUND(O7/P7,1),"") -> 9.1
A8: Retentor 1942 | B8: 1942 | C8: Retentor | D8: 558 | E8: 8 | F8: 12.32 | G8: =D8*E8 -> 4464 | H8: =D8*F8 -> 6874.56 | I8: =IF(F8>0,H8-G8,"") -> 2410.56 | J8: =IF(H8>0,I8/H8,"") -> 0.35064935 | K8: =IF(G$39>0,G8/G$39,0) -> 0.037092278 | L8: 168 | M8: 0 | N8: 2 | O8: =D8+L8+M8+N8 -> 728 | P8: 78 | Q8: =IF(P8>0,ROUND(O8/P8,1),"") -> 9.3
A9: Retentor 3044 | B9: 3044 | C9: Retentor | D9: 483 | E9: 8.5 | F9: 13.38 | G9: =D9*E9 -> 4105.5 | H9: =D9*F9 -> 6462.54 | I9: =IF(F9>0,H9-G9,"") -> 2357.04 | J9: =IF(H9>0,I9/H9,"") -> 0.36472347 | K9: =IF(G$39>0,G9/G$39,0) -> 0.034113429 | L9: 88 | M9: 0 | N9: 2 | O9: =D9+L9+M9+N9 -> 573 | P9: 88 | Q9: =IF(P9>0,ROUND(O9/P9,1),"") -> 6.5
A10: Retentor 2283 | B10: 2283 | C10: Retentor | D10: 268 | E10: 15 | F10: 28.18 | G10: =D10*E10 -> 4020 | H10: =D10*F10 -> 7552.24 | I10: =IF(F10>0,H10-G10,"") -> 3532.24 | J10: =IF(H10>0,I10/H10,"") -> 0.46770759 | K10: =IF(G$39>0,G10/G$39,0) -> 0.033402992 | L10: 36 | M10: 0 | N10: 1 | O10: =D10+L10+M10+N10 -> 305 | P10: 23 | Q10: =IF(P10>0,ROUND(O10/P10,1),"") -> 13.3
A11: Jogo de Anel 7224 0,50 | B11: 7224 0,50 | C11: Jogo de Anel | D11: 51 | E11: 75 | F11: 172.55 | G11: =D11*E11 -> 3825 | H11: =D11*F11 -> 8800.05 | I11: =IF(F11>0,H11-G11,"") -> 4975.05 | J11: =IF(H11>0,I11/H11,"") -> 0.56534338 | K11: =IF(G$39>0,G11/G$39,0) -> 0.031782698 | L11: 0 | M11: 0 | N11: 0 | O11: =D11+L11+M11+N11 -> 51 | P11: 0 | Q11: =IF(P11>0,ROUND(O11/P11,1),"")
A12: 2900 | B12: 2900 | D12: 50 | E12: 75 | G12: =D12*E12 -> 3750 | H12: =D12*F12 -> 0 | I12: =IF(F12>0,H12-G12,"") | J12: =IF(H12>0,I12/H12,"") | K12: =IF(G$39>0,G12/G$39,0) -> 0.031159508 | L12: 0 | M12: 0 | N12: 0 | O12: =D12+L12+M12+N12 -> 50 | P12: 0 | Q12: =IF(P12>0,ROUND(O12/P12,1),"")
A13: Retentor 5601 | B13: 5601 | C13: Retentor | D13: 148 | E13: 25 | F13: 38.88 | G13: =D13*E13 -> 3700 | H13: =D13*F13 -> 5754.24 | I13: =IF(F13>0,H13-G13,"") -> 2054.24 | J13: =IF(H13>0,I13/H13,"") -> 0.35699588 | K13: =IF(G$39>0,G13/G$39,0) -> 0.030744047 | L13: 27 | M13: 60 | N13: 0 | O13: =D13+L13+M13+N13 -> 235 | P13: 57 | Q13: =IF(P13>0,ROUND(O13/P13,1),"") -> 4.1
A14: Retentor 5502 | B14: 5502 | C14: Retentor | D14: 44 | E14: 70 | F14: 119.3 | G14: =D14*E14 -> 3080 | H14: =D14*F14 -> 5249.2 | I14: =IF(F14>0,H14-G14,"") -> 2169.2 | J14: =IF(H14>0,I14/H14,"") -> 0.41324392 | K14: =IF(G$39>0,G14/G$39,0) -> 0.025592342 | L14: 13 | M14: 0 | N14: 0 | O14: =D14+L14+M14+N14 -> 57 | P14: 9 | Q14: =IF(P14>0,ROUND(O14/P14,1),"") -> 6.3
A15: Retentor 2370 | B15: 2370 | C15: Retentor | D15: 434 | E15: 7 | F15: 10.3 | G15: =D15*E15 -> 3038 | H15: =D15*F15 -> 4470.2 | I15: =IF(F15>0,H15-G15,"") -> 1432.2 | J15: =IF(H15>0,I15/H15,"") -> 0.32038835 | K15: =IF(G$39>0,G15/G$39,0) -> 0.025243356 | L15: 27 | M15: 100 | N15: 0 | O15: =D15+L15+M15+N15 -> 561 | P15: 85 | Q15: =IF(P15>0,ROUND(O15/P15,1),"") -> 6.6
A16: Vedadores 9203 | B16: 9203 | C16: Vedador | D16: 318 | E16: 9 | F16: 13.36 | G16: =D16*E16 -> 2862 | H16: =D16*F16 -> 4248.48 | I16: =IF(F16>0,H16-G16,"") -> 1386.48 | J16: =IF(H16>0,I16/H16,"") -> 0.32634731 | K16: =IF(G$39>0,G16/G$39,0) -> 0.023780936 | L16: 201 | M16: 0 | N16: 1 | O16: =D16+L16+M16+N16 -> 520 | P16: 292 | Q16: =IF(P16>0,ROUND(O16/P16,1),"") -> 1.8
A17: Retentor 5245 | B17: 5245 | C17: Retentor | D17: 50 | E17: 55 | F17: 68.35 | G17: =D17*E17 -> 2750 | H17: =D17*F17 -> 3417.5 | I17: =IF(F17>0,H17-G17,"") -> 667.5 | J17: =IF(H17>0,I17/H17,"") -> 0.19531822 | K17: =IF(G$39>0,G17/G$39,0) -> 0.022850306 | L17: 84 | M17: 63 | N17: 9 | O17: =D17+L17+M17+N17 -> 206 | P17: 347 | Q17: =IF(P17>0,ROUND(O17/P17,1),"") -> 0.6
A18: Jogo de Anel 7224 STD | B18: 7224 STD | C18: Jogo de Anel | D18: 35 | E18: 75 | F18: 126.81 | G18: =D18*E18 -> 2625 | H18: =D18*F18 -> 4438.35 | I18: =IF(F18>0,H18-G18,"") -> 1813.35 | J18: =IF(H18>0,I18/H18,"") -> 0.40856399 | K18: =IF(G$39>0,G18/G$39,0) -> 0.021811655 | L18: 2 | M18: 20 | N18: 0 | O18: =D18+L18+M18+N18 -> 57 | P18: 44 | Q18: =IF(P18>0,ROUND(O18/P18,1),"") -> 1.3
A19: Retentor 5699 | B19: 5699 | C19: Retentor | D19: 27 | E19: 95 | F19: 231.86 | G19: =D19*E19 -> 2565 | H19: =D19*F19 -> 6260.22 | I19: =IF(F19>0,H19-G19,"") -> 3695.22 | J19: =IF(H19>0,I19/H19,"") -> 0.59026999 | K19: =IF(G$39>0,G19/G$39,0) -> 0.021313103 | L19: 23 | M19: 0 | N19: 0 | O19: =D19+L19+M19+N19 -> 50 | P19: 17 | Q19: =IF(P19>0,ROUND(O19/P19,1),"") -> 2.9
A20: Retentor 2544 | B20: 2544 | C20: Retentor | D20: 211 | E20: 12 | F20: 18.31 | G20: =D20*E20 -> 2532 | H20: =D20*F20 -> 3863.41 | I20: =IF(F20>0,H20-G20,"") -> 1331.41 | J20: =IF(H20>0,I20/H20,"") -> 0.34462043 | K20: =IF(G$39>0,G20/G$39,0) -> 0.0210389 | L20: 8 | M20: 50 | N20: 1 | O20: =D20+L20+M20+N20 -> 270 | P20: 49 | Q20: =IF(P20>0,ROUND(O20/P20,1),"") -> 5.5
A21: Retentor 2371 (Shopee) | B21: 2371 | C21: Retentor | D21: 359 | E21: 7 | F21: 20 | G21: =D21*E21 -> 2513 | H21: =D21*F21 -> 7180 | I21: =IF(F21>0,H21-G21,"") -> 4667 | J21: =IF(H21>0,I21/H21,"") -> 0.65 | K21: =IF(G$39>0,G21/G$39,0) -> 0.020881025 | L21: 13 | M21: 0 | N21: 0 | O21: =D21+L21+M21+N21 -> 372 | P21: 16 | Q21: =IF(P21>0,ROUND(O21/P21,1),"") -> 23.2
A22: Retentor 2178 | B22: 2178 | C22: Retentor | D22: 311 | E22: 8 | F22: 11.18 | G22: =D22*E22 -> 2488 | H22: =D22*F22 -> 3476.98 | I22: =IF(F22>0,H22-G22,"") -> 988.98 | J22: =IF(H22>0,I22/H22,"") -> 0.28443649 | K22: =IF(G$39>0,G22/G$39,0) -> 0.020673295 | L22: 163 | M22: 0 | N22: 4 | O22: =D22+L22+M22+N22 -> 478 | P22: 448 | Q22: =IF(P22>0,ROUND(O22/P22,1),"") -> 1.1
A23: Retentor 5801 | B23: 5801 | C23: Retentor | D23: 29 | E23: 85 | F23: 145.76 | G23: =D23*E23 -> 2465 | H23: =D23*F23 -> 4227.04 | I23: =IF(F23>0,H23-G23,"") -> 1762.04 | J23: =IF(H23>0,I23/H23,"") -> 0.41684962 | K23: =IF(G$39>0,G23/G$39,0) -> 0.020482183 | L23: 5 | M23: 125 | N23: 8 | O23: =D23+L23+M23+N23 -> 167 | P23: 234 | Q23: =IF(P23>0,ROUND(O23/P23,1),"") -> 0.7
A24: Retentor 2374 | B24: 2374 | C24: Retentor | D24: 297 | E24: 8 | F24: 16.89 | G24: =D24*E24 -> 2376 | H24: =D24*F24 -> 5016.33 | I24: =IF(F24>0,H24-G24,"") -> 2640.33 | J24: =IF(H24>0,I24/H24,"") -> 0.52634695 | K24: =IF(G$39>0,G24/G$39,0) -> 0.019742664 | L24: 61 | M24: 0 | N24: 0 | O24: =D24+L24+M24+N24 -> 358 | P24: 107 | Q24: =IF(P24>0,ROUND(O24/P24,1),"") -> 3.3
A25: Anel SDA 7092 | B25: 7092 | C25: Anéis | D25: 22 | E25: 75 | F25: 127.94 | G25: =D25*E25 -> 1650 | H25: =D25*F25 -> 2814.68 | I25: =IF(F25>0,H25-G25,"") -> 1164.68 | J25: =IF(H25>0,I25/H25,"") -> 0.41378771 | K25: =IF(G$39>0,G25/G$39,0) -> 0.013710183 | L25: 37 | M25: 0 | N25: 0 | O25: =D25+L25+M25+N25 -> 59 | P25: 30 | Q25: =IF(P25>0,ROUND(O25/P25,1),"") -> 2
A26: 8566 STD | B26: 8566 STD | D26: 20 | E26: 75 | G26: =D26*E26 -> 1500 | H26: =D26*F26 -> 0 | I26: =IF(F26>0,H26-G26,"") | J26: =IF(H26>0,I26/H26,"") | K26: =IF(G$39>0,G26/G$39,0) -> 0.012463803 | L26: 0 | M26: 0 | N26: 0 | O26: =D26+L26+M26+N26 -> 20 | P26: 0 | Q26: =IF(P26>0,ROUND(O26/P26,1),"")
A27: Anéis 9403 STD | B27: 9403 STD | C27: Anéis | D27: 20 | E27: 75 | G27: =D27*E27 -> 1500 | H27: =D27*F27 -> 0 | I27: =IF(F27>0,H27-G27,"") | J27: =IF(H27>0,I27/H27,"") | K27: =IF(G$39>0,G27/G$39,0) -> 0.012463803 | L27: 0 | M27: 0 | N27: 0 | O27: =D27+L27+M27+N27 -> 20 | P27: 0 | Q27: =IF(P27>0,ROUND(O27/P27,1),"")
A28: Retentor 2400 | B28: 2400 | C28: Retentor | D28: 101 | E28: 14 | F28: 29.43 | G28: =D28*E28 -> 1414 | H28: =D28*F28 -> 2972.43 | I28: =IF(F28>0,H28-G28,"") -> 1558.43 | J28: =IF(H28>0,I28/H28,"") -> 0.52429494 | K28: =IF(G$39>0,G28/G$39,0) -> 0.011749212 | L28: 14 | M28: 30 | N28: 0 | O28: =D28+L28+M28+N28 -> 145 | P28: 32 | Q28: =IF(P28>0,ROUND(O28/P28,1),"") -> 4.5
A29: Retentor 1135 | B29: 1135 | C29: Retentor | D29: 116 | E29: 12 | F29: 31.13 | G29: =D29*E29 -> 1392 | H29: =D29*F29 -> 3611.08 | I29: =IF(F29>0,H29-G29,"") -> 2219.08 | J29: =IF(H29>0,I29/H29,"") -> 0.61451976 | K29: =IF(G$39>0,G29/G$39,0) -> 0.011566409 | L29: 11 | M29: 0 | N29: 0 | O29: =D29+L29+M29+N29 -> 127 | P29: 5 | Q29: =IF(P29>0,ROUND(O29/P29,1),"") -> 25.4
A30: Retentor 2075 | B30: 2075 | C30: Retentor | D30: 124 | E30: 8 | F30: 13.42 | G30: =D30*E30 -> 992 | H30: =D30*F30 -> 1664.08 | I30: =IF(F30>0,H30-G30,"") -> 672.08 | J30: =IF(H30>0,I30/H30,"") -> 0.40387481 | K30: =IF(G$39>0,G30/G$39,0) -> 0.0082427284 | L30: 7 | M30: 0 | N30: 0 | O30: =D30+L30+M30+N30 -> 131 | P30: 2 | Q30: =IF(P30>0,ROUND(O30/P30,1),"") -> 65.5
A31: Bronzina de Biela SBB 1035-J 0,25 | B31: 1035-J | C31: Bronzina | D31: 22 | E31: 32 | F31: 69.25 | G31: =D31*E31 -> 704 | H31: =D31*F31 -> 1523.5 | I31: =IF(F31>0,H31-G31,"") -> 819.5 | J31: =IF(H31>0,I31/H31,"") -> 0.53790614 | K31: =IF(G$39>0,G31/G$39,0) -> 0.0058496782 | L31: 18 | M31: 0 | N31: 0 | O31: =D31+L31+M31+N31 -> 40 | P31: 61 | Q31: =IF(P31>0,ROUND(O31/P31,1),"") -> 0.7
A32: Retentor 2317 | B32: 2317 | C32: Retentor | D32: 72 | E32: 8 | F32: 25.62 | G32: =D32*E32 -> 576 | H32: =D32*F32 -> 1844.64 | I32: =IF(F32>0,H32-G32,"") -> 1268.64 | J32: =IF(H32>0,I32/H32,"") -> 0.68774395 | K32: =IF(G$39>0,G32/G$39,0) -> 0.0047861004 | L32: 19 | M32: 20 | N32: 0 | O32: =D32+L32+M32+N32 -> 111 | P32: 28 | Q32: =IF(P32>0,ROUND(O32/P32,1),"") -> 4
A33: Retentor 2373 | B33: 2373 | C33: Retentor | D33: 94 | E33: 6 | F33: 22.16 | G33: =D33*E33 -> 564 | H33: =D33*F33 -> 2083.04 | I33: =IF(F33>0,H33-G33,"") -> 1519.04 | J33: =IF(H33>0,I33/H33,"") -> 0.72924188 | K33: =IF(G$39>0,G33/G$39,0) -> 0.0046863899 | L33: 21 | M33: 40 | N33: 0 | O33: =D33+L33+M33+N33 -> 155 | P33: 38 | Q33: =IF(P33>0,ROUND(O33/P33,1),"") -> 4.1
A34: Anéis 9200 STD | B34: 9200 STD | C34: Anéis | D34: 7 | E34: 75 | F34: 156.03 | G34: =D34*E34 -> 525 | H34: =D34*F34 -> 1092.21 | I34: =IF(F34>0,H34-G34,"") -> 567.21 | J34: =IF(H34>0,I34/H34,"") -> 0.51932321 | K34: =IF(G$39>0,G34/G$39,0) -> 0.0043623311 | L34: 0 | M34: 0 | N34: 0 | O34: =D34+L34+M34+N34 -> 7 | P34: 0 | Q34: =IF(P34>0,ROUND(O34/P34,1),"")
A35: Retentor 2539 | B35: 2539 | C35: Retentor | D35: 35 | E35: 8 | F35: 21.5 | G35: =D35*E35 -> 280 | H35: =D35*F35 -> 752.5 | I35: =IF(F35>0,H35-G35,"") -> 472.5 | J35: =IF(H35>0,I35/H35,"") -> 0.62790698 | K35: =IF(G$39>0,G35/G$39,0) -> 0.0023265766 | L35: 33 | M35: 0 | N35: 2 | O35: =D35+L35+M35+N35 -> 70 | P35: 8 | Q35: =IF(P35>0,ROUND(O35/P35,1),"") -> 8.8
A36: Retentor 5702 | B36: 5702 | C36: Retentor | D36: 3 | E36: 50 | F36: 57.36 | G36: =D36*E36 -> 150 | H36: =D36*F36 -> 172.08 | I36: =IF(F36>0,H36-G36,"") -> 22.08 | J36: =IF(H36>0,I36/H36,"") -> 0.12831241 | K36: =IF(G$39>0,G36/G$39,0) -> 0.0012463803 | L36: 0 | M36: 0 | N36: 0 | O36: =D36+L36+M36+N36 -> 3 | P36: 3 | Q36: =IF(P36>0,ROUND(O36/P36,1),"") -> 1
A37: Retentor 5266 | B37: 5266 | C37: Retentor | D37: 15 | E37: 8 | F37: 25.62 | G37: =D37*E37 -> 120 | H37: =D37*F37 -> 384.3 | I37: =IF(F37>0,H37-G37,"") -> 264.3 | J37: =IF(H37>0,I37/H37,"") -> 0.68774395 | K37: =IF(G$39>0,G37/G$39,0) -> 0.00099710424 | L37: 26 | M37: 0 | N37: 0 | O37: =D37+L37+M37+N37 -> 41 | P37: 36 | Q37: =IF(P37>0,ROUND(O37/P37,1),"") -> 1.1
A38: Anéis 8126 0,50 | B38: 8126 0,50 | C38: Anéis | D38: 1 | E38: 75 | F38: 144.9 | G38: =D38*E38 -> 75 | H38: =D38*F38 -> 144.9 | I38: =IF(F38>0,H38-G38,"") -> 69.9 | J38: =IF(H38>0,I38/H38,"") -> 0.48240166 | K38: =IF(G$39>0,G38/G$39,0) -> 0.00062319015 | L38: 0 | M38: 0 | N38: 0 | O38: =D38+L38+M38+N38 -> 1 | P38: 0 | Q38: =IF(P38>0,ROUND(O38/P38,1),"")
A39: TOTAL | D39: =SUM(D2:D38) -> 6474 | G39: =SUM(G2:G38) -> 120348.5 | H39: =SUM(H2:H38) -> 203232.24 | I39: =SUM(I2:I38) -> 89633.74 | J39: =IF(H39>0,I39/H39,"") -> 0.44104095 | K39: =SUM(K2:K38) -> 1 | L39: =SUM(L2:L38) -> 1660 | M39: =SUM(M2:M38) -> 648 | N39: =SUM(N2:N38) -> 34 | O39: =SUM(O2:O38) -> 8816 | P39: =SUM(P2:P38) -> 2563
